gempaterkini/__init__.py
latestearthquakenewsindonesia-0.7.dist-info/LICENSE
latestearthquakenewsindonesia-0.7.dist-info/METADATA
latestearthquakenewsindonesia-0.7.dist-info/WHEEL
latestearthquakenewsindonesia-0.7.dist-info/top_level.txt
latestearthquakenewsindonesia-0.7.dist-info/RECORD
